devpy/__init__.py
devpy/log.py
devpy/tb.py
devpy/temp.py
devpy/develop/__init__.py
devpy-0.1.7.dist-info/DESCRIPTION.rst
devpy-0.1.7.dist-info/METADATA
devpy-0.1.7.dist-info/RECORD
devpy-0.1.7.dist-info/WHEEL
devpy-0.1.7.dist-info/metadata.json
devpy-0.1.7.dist-info/top_level.txt
