Metadata-Version: 2.0
Name: devpy
Version: 0.1.7
Summary: Tools to help development and debugging
Home-page: https://github.com/sametmax/devpy/
Author: Sam & Max
Author-email: lesametlemax@gmail.com
License: MIT
Keywords: devpy dev
Platform: UNKNOWN
Classifier: Development Status :: 1 - Planning
Classifier: Intended Audience :: Developers
Classifier: Natural Language :: English
Classifier: Programming Language :: Python :: 3.6
Classifier: Programming Language :: Python :: 3 :: Only
Classifier: Operating System :: OS Independent
Requires-Dist: Pygments
Requires-Dist: colorama
Requires-Dist: colored-traceback
Requires-Dist: colorlog
